report_automation/__init__.py
report_automation/report_generator.py
report_automation/te_net.py
report_automation 2/__init__.py
report_automation 2/report_generator.py
report_automation 2/te_net.py
dimondat_report_automation-0.0.1.dist-info/LICENSE
dimondat_report_automation-0.0.1.dist-info/METADATA
dimondat_report_automation-0.0.1.dist-info/WHEEL
dimondat_report_automation-0.0.1.dist-info/top_level.txt
dimondat_report_automation-0.0.1.dist-info/RECORD
