Metadata-Version: 2.1
Name: dimondat-report-automation
Version: 0.0.1
Summary: A small example package
Home-page: UNKNOWN
Author: Dimondat
Author-email: author@example.com
License: UNKNOWN
Platform: UNKNOWN
Requires-Python: >=3.6
Requires-Dist: numpy
